cycleflow/__init__.py
cycleflow/cycleflow.py
CycleFlow-1.2.dist-info/LICENSE
CycleFlow-1.2.dist-info/METADATA
CycleFlow-1.2.dist-info/WHEEL
CycleFlow-1.2.dist-info/top_level.txt
CycleFlow-1.2.dist-info/RECORD
