Metadata-Version: 2.1
Name: CycleFlow
Version: 1.2
Summary: Quantification of Cell Cycle length and cycling heterogeneity
Home-page: https://github.com/AdrienJolly/CycleFlow
Author: Adrien Jolly and Nils B. Becker
Author-email: a.jolly@dkfz.de
License: UNKNOWN
Platform: UNKNOWN
Classifier: Programming Language :: Python :: 3
Classifier: License :: OSI Approved :: MIT License
Classifier: Operating System :: OS Independent
Requires-Dist: numpy
Requires-Dist: numba
Requires-Dist: scipy
Requires-Dist: pandas
